AUTHOR
LICENSE
MANIFEST.in
README
VERSION
setup.py
gelid_http.egg-info/PKG-INFO
gelid_http.egg-info/SOURCES.txt
gelid_http.egg-info/dependency_links.txt
gelid_http.egg-info/pbr.json
gelid_http.egg-info/requires.txt
gelid_http.egg-info/top_level.txt
gelidhttp/__init__.py
gelidhttp/http.py
gelidhttp/log.py
gelidhttp/parameter.py
gelidhttp/request.py
gelidhttp/response.py
gelidhttp/settings.py
gelidhttp/utils.py