Metadata-Version: 1.0
Name: gelid-http
Version: 1.4
Summary: 为python-gelid提供简单http请求服务
Home-page: https://github.com/lvjiyong/python-gelid
Author: lvjiyong
Author-email: lvjiyong@gmail.com
License: Apache2.0
Platform: any
